LICENSE
MANIFEST.in
README.md
setup.py
pyblebox/__init__.py
pyblebox/cli.py
pyblebox/config.py
pyblebox/exceptions.py
pyblebox/wlightboxs.py
python_blebox.egg-info/PKG-INFO
python_blebox.egg-info/SOURCES.txt
python_blebox.egg-info/dependency_links.txt
python_blebox.egg-info/entry_points.txt
python_blebox.egg-info/requires.txt
python_blebox.egg-info/top_level.txt
python_blebox.egg-info/zip-safe